{
	"videoType": 0,
	"videos": [

        {
            "width": 1920,
            "height": 1080,
            "name": "Videos/GDL_Market1.mp4_HAP.mov",
            "alias": "left",
            "drawx": 0,
            "drawy": 0
        },
        {
            "width": 1920,
            "height": 1080,
            "name": "Videos/GDL_Market2.mp4_HAP.mov",
            "alias": "front",
            "drawx": 0,
            "drawy": 0
        },

        {
            "width": 1920,
            "height": 1080,
            "name": "Videos/GDL_Market3.mp4_HAP.mov",
            "alias": "right",
            "drawx": 0,
            "drawy": 0
        },
        {
            "width": 1920,
            "height": 1080,
            "name": "Videos/within_world_is_fufu2 (1)_HAP.mov",
            "alias": "display",
            "drawx": 0,
            "drawy": 0
        }


	]
}
